nonebot_plugin_bnhhsh/__init__.py
nonebot_plugin_bnhhsh/__main__.py
nonebot_plugin_bnhhsh/bnhhsh/.git
nonebot_plugin_bnhhsh/bnhhsh/LICENSE
nonebot_plugin_bnhhsh/bnhhsh/bnhhsh/__init__.py
nonebot_plugin_bnhhsh/bnhhsh/bnhhsh/data/常用汉字.json
nonebot_plugin_bnhhsh/bnhhsh/bnhhsh/data/现代汉语常用词表.json
nonebot_plugin_bnhhsh/bnhhsh/bnhhsh/data/色情词库.json
nonebot_plugin_bnhhsh/bnhhsh/bnhhsh/data/色情词库_数据增强.json
nonebot_plugin_bnhhsh/bnhhsh/bnhhsh/data/莉沫词库.json
nonebot_plugin_bnhhsh/bnhhsh/img/s.jpg
nonebot_plugin_bnhhsh/bnhhsh/readme.md
nonebot_plugin_bnhhsh/bnhhsh/setup.py
nonebot_plugin_bnhhsh/config.py
nonebot_plugin_bnhhsh-0.1.2.post1.dist-info/WHEEL
nonebot_plugin_bnhhsh-0.1.2.post1.dist-info/LICENSE
nonebot_plugin_bnhhsh-0.1.2.post1.dist-info/METADATA
nonebot_plugin_bnhhsh-0.1.2.post1.dist-info/RECORD
