Metadata-Version: 2.1
Name: nonebot-plugin-bnhhsh
Version: 0.1.2.post1
Summary: Se-se!
License: MIT
Author: student_2333
Author-email: lgc2333@126.com
Requires-Python: >=3.8,<4.0
Classifier: License :: OSI Approved :: MIT License
Classifier: Programming Language :: Python :: 3
Classifier: Programming Language :: Python :: 3.8
Classifier: Programming Language :: Python :: 3.9
Classifier: Programming Language :: Python :: 3.10
Classifier: Programming Language :: Python :: 3.11
Requires-Dist: nonebot-adapter-onebot (>=2.1.3,<3.0.0)
Requires-Dist: nonebot2 (>=2.0.0b4)
Requires-Dist: pathlib (>=1.0.1,<2.0.0)
Requires-Dist: pypinyin (>=0.42.0)
Requires-Dist: unvcode (>=1.0.0,<2.0.0)
